gptopen/__init__.py
gptopen-0.0.2.dist-info/LICENSE
gptopen-0.0.2.dist-info/METADATA
gptopen-0.0.2.dist-info/WHEEL
gptopen-0.0.2.dist-info/top_level.txt
gptopen-0.0.2.dist-info/RECORD
