Metadata-Version: 2.1
Name: gptopen
Version: 0.0.2
Summary: GPT+ Open Platform SDK
Author-email: ImYrS <i@imyrs.com>
Project-URL: Homepage, https://github.com/ImYrS/gpto-sdk
Classifier: Programming Language :: Python :: 3
Classifier: License :: OSI Approved :: MIT License
Classifier: Operating System :: OS Independent
Requires-Python: >=3.6
License-File: LICENSE
Requires-Dist: requests (>=2.30.0)
